{
  "id": "heidarmirhajisadati/german-vehicle-price-and-efficiency-dataset",
  "id_no": 5982058,
  "datasetSlugNullable": "german-vehicle-price-and-efficiency-dataset",
  "ownerUserNullable": "heidarmirhajisadati",
  "usabilityRatingNullable": 1.0,
  "titleNullable": "German Vehicle Price and Efficiency Data",
  "subtitleNullable": "German Vehicle Price",
  "descriptionNullable": "## Introduction:\n\n**In this dataset, I have compiled a dataset of 500 records representing key details of cars in the German automotive market.** \nThis dataset is structured to reflect common attributes of vehicles available in Germany, providing a valuable foundation for analyzing patterns in pricing, fuel efficiency, and other key aspects of the German car market.\n\n### Column Descriptions:\n\n**Brand:** Represents the car\u2019s brand, with options including popular German manufacturers such as BMW, Mercedes, Audi, Volkswagen, Porsche, and Opel.\n\n**Model:** Details the specific model within each brand, such as the BMW 3 Series, Mercedes C-Class, and Audi A3.\nYear: The manufacturing year of each vehicle, ranging from 2005 to 2023.\n\n**Mileage:** The total kilometers each car has traveled, with values ranging from 5,000 to 300,000 km, capturing a broad spectrum of vehicle usage.\n\n**Fuel Type:** Specifies the type of fuel the car uses, including Petrol, Diesel, Electric, and Hybrid options.\n\n**Fuel Consumption (L/100km):** Represents the vehicle\u2019s average fuel consumption, in liters per 100 kilometers, ranging between 3.0 to 12.0 L/100km.\n\n**Horsepower (HP):** The engine\u2019s power rating in horsepower, with values from 70 to 500 HP.\n\n**Transmission:** Indicates whether the car has a Manual or Automatic transmission.\n\n**Price (\u20ac):** The price of the vehicle in euros, ranging from \u20ac5,000 to \u20ac100,000, providing a broad view of vehicle costs across different car types.\n\n**City:** The location in Germany where each vehicle is available, including cities like Berlin, Munich, Hamburg, Cologne, and Frankfurt.",
  "datasetId": 5982058,
  "datasetSlug": "german-vehicle-price-and-efficiency-dataset",
  "hasDatasetSlug": true,
  "ownerUser": "heidarmirhajisadati",
  "hasOwnerUser": true,
  "usabilityRating": 1.0,
  "hasUsabilityRating": true,
  "totalViews": 2349,
  "totalVotes": 69,
  "totalDownloads": 505,
  "title": "German Vehicle Price and Efficiency Data",
  "hasTitle": true,
  "subtitle": "German Vehicle Price",
  "hasSubtitle": true,
  "description": "## Introduction:\n\n**In this dataset, I have compiled a dataset of 500 records representing key details of cars in the German automotive market.** \nThis dataset is structured to reflect common attributes of vehicles available in Germany, providing a valuable foundation for analyzing patterns in pricing, fuel efficiency, and other key aspects of the German car market.\n\n### Column Descriptions:\n\n**Brand:** Represents the car\u2019s brand, with options including popular German manufacturers such as BMW, Mercedes, Audi, Volkswagen, Porsche, and Opel.\n\n**Model:** Details the specific model within each brand, such as the BMW 3 Series, Mercedes C-Class, and Audi A3.\nYear: The manufacturing year of each vehicle, ranging from 2005 to 2023.\n\n**Mileage:** The total kilometers each car has traveled, with values ranging from 5,000 to 300,000 km, capturing a broad spectrum of vehicle usage.\n\n**Fuel Type:** Specifies the type of fuel the car uses, including Petrol, Diesel, Electric, and Hybrid options.\n\n**Fuel Consumption (L/100km):** Represents the vehicle\u2019s average fuel consumption, in liters per 100 kilometers, ranging between 3.0 to 12.0 L/100km.\n\n**Horsepower (HP):** The engine\u2019s power rating in horsepower, with values from 70 to 500 HP.\n\n**Transmission:** Indicates whether the car has a Manual or Automatic transmission.\n\n**Price (\u20ac):** The price of the vehicle in euros, ranging from \u20ac5,000 to \u20ac100,000, providing a broad view of vehicle costs across different car types.\n\n**City:** The location in Germany where each vehicle is available, including cities like Berlin, Munich, Hamburg, Cologne, and Frankfurt.",
  "hasDescription": true,
  "isPrivate": false,
  "keywords": [
    "marketing"
  ],
  "licenses": [
    {
      "nameNullable": "MIT",
      "name": "MIT",
      "hasName": true
    }
  ],
  "collaborators": [],
  "data": []
}